{
  "contracts": [
    {
      "address": "0x7039cd6D7966672F194E8139074C3D5c4e6DCf65",
      "decimals": 9,
      "name": "Super Trump",
      "network": "evm-1",
      "symbol": "STRUMP",
      "tags": [
        "mainnet"
      ]
    }
  ],
  "id": "strump-0",
  "images": {
    "png128": true,
    "png256": true,
    "png32": true,
    "png64": true,
    "svg": false
  },
  "name": "Super Trump",
  "references": [
    {
      "id": "coingecko",
      "url": "https://www.coingecko.com/en/coins/super-trump"
    },
    {
      "id": "coinmarketcap",
      "url": "https://coinmarketcap.com/currencies/super-trump-io"
    }
  ],
  "tags": []
}
