{
  "contracts": [
    {
      "address": "0x570A5D26f7765Ecb712C0924E4De545B89fD43dF",
      "decimals": 18,
      "name": "SOLANA",
      "network": "evm-56",
      "symbol": "SOL",
      "tags": [
        "mainnet"
      ]
    }
  ],
  "id": "wsol-0",
  "images": {
    "png128": true,
    "png256": true,
    "png32": true,
    "png64": true,
    "svg": true
  },
  "name": "SOLANA",
  "references": [
    {
      "id": "coingecko",
      "url": "https://www.coingecko.com/en/coins/wrapped-solana"
    },
    {
      "id": "coinmarketcap",
      "url": "https://coinmarketcap.com/currencies/wrapped-solana"
    }
  ],
  "tags": []
}
