{
  "contracts": [
    {
      "address": "0x594DaaD7D77592a2b97b725A7AD59D7E188b5bFa",
      "decimals": 18,
      "name": "Apu Apustaja",
      "network": "evm-1",
      "symbol": "APU",
      "tags": [
        "mainnet"
      ]
    }
  ],
  "id": "apu-0",
  "images": {
    "png128": true,
    "png256": true,
    "png32": true,
    "png64": true,
    "svg": false
  },
  "name": "Apu Apustaja",
  "references": [
    {
      "id": "coingecko",
      "url": "https://www.coingecko.com/en/coins/apu-apustaja"
    },
    {
      "id": "coinmarketcap",
      "url": "https://coinmarketcap.com/currencies/apu-apustaja"
    }
  ],
  "tags": []
}
