{
  "contracts": [
    {
      "address": "0x1c1b06405058AbE02e4748753aeD1458BEFEE3B9",
      "decimals": 18,
      "name": "Wrapped Bifrost",
      "network": "evm-3068",
      "symbol": "WBFC",
      "tags": [
        "mainnet",
        "wrapped-coin"
      ]
    },
    {
      "address": "0x1745F24d85192545E5eD1c9574782d067D3Fda09",
      "decimals": 18,
      "name": "Wrapped Bifrost",
      "network": "evm-49088",
      "symbol": "WBFC",
      "tags": [
        "testnet",
        "wrapped-coin"
      ]
    }
  ],
  "id": "wbfc-0",
  "images": {
    "png128": true,
    "png256": true,
    "png32": true,
    "png64": true,
    "svg": true
  },
  "name": "Wrapped Bifrost",
  "references": [
    {
      "id": "coingecko",
      "url": "https://www.coingecko.com/en/coins/"
    },
    {
      "id": "coinmarketcap",
      "url": "https://coinmarketcap.com/currencies/"
    }
  ],
  "tags": []
}
